cf/CF.py
cf/Cluster.py
cf/UserBased.py
cf/__init__.py
cf/clustering.py
cf/recommendation.py
cf/user_based_cf.py
cf_pkg-0.0.4.dist-info/METADATA
cf_pkg-0.0.4.dist-info/WHEEL
cf_pkg-0.0.4.dist-info/top_level.txt
cf_pkg-0.0.4.dist-info/RECORD
