Metadata-Version: 2.1
Name: cf-pkg
Version: 0.0.4
Summary: clustering+collaborative filtering+recommend system
Home-page: UNKNOWN
Author: Tomsawyerhu
Author-email: 1095549886@qq.com
License: UNKNOWN
Platform: UNKNOWN
Classifier: Programming Language :: Python :: 3
Classifier: License :: OSI Approved :: MIT License
Classifier: Operating System :: OS Independent
Requires-Python: >=3.6
Requires-Dist: numpy
